shared_dyamic_listing/__init__.py
shared_dyamic_listing/models.py
shared_dyamic_listing/serializers.py
shared_dyamic_listing/services.py
shared_dyamic_listing-0.1.0.dist-info/LICENSE.txt
shared_dyamic_listing-0.1.0.dist-info/METADATA
shared_dyamic_listing-0.1.0.dist-info/WHEEL
shared_dyamic_listing-0.1.0.dist-info/top_level.txt
shared_dyamic_listing-0.1.0.dist-info/RECORD
