Metadata-Version: 2.1
Name: shared_dyamic_listing
Version: 0.1.0
Summary: This is Dynamically setup the preferences for by user and business
Home-page: https://github.com/rubnawazgondal/expertmedicalpage-aks.git
Author: Muhammad Shahbaz
Author-email: ds.shahbaz.rajput@example.com
Classifier: Programming Language :: Python :: 3
Classifier: License :: OSI Approved :: MIT License
Classifier: Operating System :: OS Independent
Requires-Python: >=3.6
License-File: LICENSE.txt
